{
  "updated": "2026-03-20T16:58:32.485202+00:00",
  "top_stories": [
    {
      "article_id": "73deb329cef8882c0f2b393198834b44",
      "title": "Rebel Audio is a new AI podcasting tool aimed at first-time creators",
      "source": "techcrunch_ai",
      "url": "https://techcrunch.com/2026/03/18/rebel-audio-is-a-new-ai-podcasting-tool-aimed-at-first-time-creators/",
      "published_date": "2026-03-18T17:15:00+00:00",
      "category": "Industry",
      "description": "Rebel Audio is a new all-in-one podcasting tool that allows creators to record podcasts, edit, clip content for social, and publish episodes, all without ever leaving the platform.",
      "author": "Lauren Forristal",
      "content": "Rebel Audio is a new all-in-one podcasting tool that allows creators to record podcasts, edit, clip content for social, and publish episodes, all without ever leaving the platform.",
      "consensus_multi_dimensional_score": {
        "relevance_score": 0.9,
        "quality_score": 0.85,
        "novelty_score": 0.8,
        "impact_score": 0.95,
        "overall_score": 0.8725,
        "confidence_mean": 0.95
      },
      "combined_deep_intelligence": {
        "analysis": {
          "fact_verification": {
            "verified_claims": [],
            "unverified_claims": [],
            "fact_check_confidence": 0.5
          },
          "bias_detection": {
            "bias_indicators": [],
            "bias_detection_score": 0.5
          },
          "credibility_assessment": {
            "credibility_factors": [],
            "credibility_score": 0.5
          },
          "impact_analysis": {
            "impact_areas": [],
            "impact_potential": 0.5
          },
          "synthesis": {
            "key_insights": [],
            "risk_factors": [],
            "enhancement_suggestions": []
          }
        },
        "score": 0.9,
        "confidence": 0.9,
        "recommendation": "ACCEPT",
        "agents_count": 1,
        "consensus_timestamp": "2026-03-20T16:58:32.443093+00:00"
      },
      "final_consensus": {
        "algorithm": "weighted_combination",
        "weighted_score": 0.74,
        "combined_confidence": 0.74,
        "decision": "ACCEPT",
        "weights": {
          "initial_consensus": 0.4,
          "deep_intelligence": 0.6
        },
        "timestamp": "2026-03-20T16:58:32.443096+00:00"
      },
      "article_type": "headline"
    },
    {
      "article_id": "1b61772b19ac21d680817977a82883ce",
      "title": "NVIDIA, Telecom Leaders Build AI Grids to Optimize Inference on Distributed Networks",
      "source": "nvidia_blog",
      "url": "https://blogs.nvidia.com/blog/telecom-ai-grids-inference/",
      "published_date": "2026-03-17T17:00:15+00:00",
      "category": "Industry",
      "description": "As AI‑native applications scale to more users, agents and devices, the telecommunications network is becoming the next frontier for distributing AI. At NVIDIA GTC 2026, leading operators in the U.S. and Asia showed that this shift is underway, announcing AI grids — geographically distributed and interconnected AI infrastructure — using their network footprint to power […]",
      "author": "Kanika Atri",
      "content": "As AI‑native applications scale to more users, agents and devices, the telecommunications network is becoming the next frontier for distributing AI. At NVIDIA GTC 2026, leading operators in the U.S. and Asia showed that this shift is underway, announcing AI grids — geographically distributed and interconnected AI infrastructure — using their network footprint to power […]",
      "consensus_multi_dimensional_score": {
        "relevance_score": 0.95,
        "quality_score": 0.9,
        "novelty_score": 0.85,
        "impact_score": 0.95,
        "overall_score": 0.9125000000000001,
        "confidence_mean": 0.95
      },
      "combined_deep_intelligence": {
        "analysis": {
          "fact_verification": {
            "verified_claims": [],
            "unverified_claims": [],
            "fact_check_confidence": 0.5
          },
          "bias_detection": {
            "bias_indicators": [],
            "bias_detection_score": 0.5
          },
          "credibility_assessment": {
            "credibility_factors": [],
            "credibility_score": 0.5
          },
          "impact_analysis": {
            "impact_areas": [],
            "impact_potential": 0.5
          },
          "synthesis": {
            "key_insights": [],
            "risk_factors": [],
            "enhancement_suggestions": []
          }
        },
        "score": 0.9,
        "confidence": 0.9,
        "recommendation": "ACCEPT",
        "agents_count": 1,
        "consensus_timestamp": "2026-03-20T16:58:32.441667+00:00"
      },
      "final_consensus": {
        "algorithm": "weighted_combination",
        "weighted_score": 0.74,
        "combined_confidence": 0.74,
        "decision": "ACCEPT",
        "weights": {
          "initial_consensus": 0.4,
          "deep_intelligence": 0.6
        },
        "timestamp": "2026-03-20T16:58:32.441670+00:00"
      },
      "article_type": "article"
    },
    {
      "article_id": "1a60d969638c2968c612163d6bfba28c",
      "title": "As Open Models Spark AI Boom, NVIDIA Jetson Brings It to Life at the Edge",
      "source": "nvidia_blog",
      "url": "https://blogs.nvidia.com/blog/jetson-generative-ai-edge-oss/",
      "published_date": "2026-03-10T16:43:40+00:00",
      "category": "Industry",
      "description": "The Cat 306 CR mini-excavator weighs just under eight tons and fits inside a standard shipping container. It’s the machine a contractor rents when the job site is tight: a utility trench near a foundation, a basement dig in a dense neighborhood. The cab is roughly the size of a phone booth. The operator sits […]",
      "author": "Chen Su",
      "content": "The Cat 306 CR mini-excavator weighs just under eight tons and fits inside a standard shipping container. It’s the machine a contractor rents when the job site is tight: a utility trench near a foundation, a basement dig in a dense neighborhood. The cab is roughly the size of a phone booth. The operator sits […]",
      "consensus_multi_dimensional_score": {
        "relevance_score": 0.95,
        "quality_score": 0.9,
        "novelty_score": 0.8,
        "impact_score": 0.98,
        "overall_score": 0.9059999999999999,
        "confidence_mean": 0.95
      },
      "combined_deep_intelligence": {
        "analysis": {
          "fact_verification": {
            "verified_claims": [],
            "unverified_claims": [],
            "fact_check_confidence": 0.5
          },
          "bias_detection": {
            "bias_indicators": [],
            "bias_detection_score": 0.5
          },
          "credibility_assessment": {
            "credibility_factors": [],
            "credibility_score": 0.5
          },
          "impact_analysis": {
            "impact_areas": [],
            "impact_potential": 0.5
          },
          "synthesis": {
            "key_insights": [],
            "risk_factors": [],
            "enhancement_suggestions": []
          }
        },
        "score": 0.9,
        "confidence": 0.9,
        "recommendation": "ACCEPT",
        "agents_count": 1,
        "consensus_timestamp": "2026-03-20T16:58:32.441997+00:00"
      },
      "final_consensus": {
        "algorithm": "weighted_combination",
        "weighted_score": 0.74,
        "combined_confidence": 0.74,
        "decision": "ACCEPT",
        "weights": {
          "initial_consensus": 0.4,
          "deep_intelligence": 0.6
        },
        "timestamp": "2026-03-20T16:58:32.442000+00:00"
      },
      "article_type": "article"
    },
    {
      "article_id": "cec6b17d9df39354deac57b2293bca77",
      "title": "How Bark.com and AWS collaborated to build a scalable video generation solution",
      "source": "aws_ml_blog",
      "url": "https://aws.amazon.com/blogs/machine-learning/how-bark-com-and-aws-collaborated-to-build-a-scalable-video-generation-solution/",
      "published_date": "2026-03-18T15:24:13+00:00",
      "category": "Industry",
      "description": "Working with the AWS Generative AI Innovation Center, Bark developed an AI-powered content generation solution that demonstrated a substantial reduction in production time in experimental trials while improving content quality scores. In this post, we walk you through the technical architecture we built, the key design decisions that contributed to success, and the measurable results achieved, giving you a blueprint for implementing similar solutions.",
      "author": "Zainab Afolabi",
      "content": "Working with the AWS Generative AI Innovation Center, Bark developed an AI-powered content generation solution that demonstrated a substantial reduction in production time in experimental trials while improving content quality scores. In this post, we walk you through the technical architecture we built, the key design decisions that contributed to success, and the measurable results achieved, giving you a blueprint for implementing similar solutions.",
      "consensus_multi_dimensional_score": {
        "relevance_score": 0.9,
        "quality_score": 0.9,
        "novelty_score": 0.9,
        "impact_score": 0.9,
        "overall_score": 0.9,
        "confidence_mean": 0.9
      },
      "combined_deep_intelligence": {
        "analysis": {
          "fact_verification": {
            "verified_claims": [],
            "unverified_claims": [],
            "fact_check_confidence": 0.5
          },
          "bias_detection": {
            "bias_indicators": [],
            "bias_detection_score": 0.5
          },
          "credibility_assessment": {
            "credibility_factors": [],
            "credibility_score": 0.5
          },
          "impact_analysis": {
            "impact_areas": [],
            "impact_potential": 0.5
          },
          "synthesis": {
            "key_insights": [],
            "risk_factors": [],
            "enhancement_suggestions": []
          }
        },
        "score": 0.9,
        "confidence": 0.9,
        "recommendation": "ACCEPT",
        "agents_count": 1,
        "consensus_timestamp": "2026-03-20T16:58:32.441054+00:00"
      },
      "final_consensus": {
        "algorithm": "weighted_combination",
        "weighted_score": 0.74,
        "combined_confidence": 0.74,
        "decision": "ACCEPT",
        "weights": {
          "initial_consensus": 0.4,
          "deep_intelligence": 0.6
        },
        "timestamp": "2026-03-20T16:58:32.441057+00:00"
      },
      "article_type": "article"
    },
    {
      "article_id": "319254e9542edcc98b8134449c5dabca",
      "title": "NIH scientists develop \"digital twin\" of eye cells to understand and treat age-related macular degeneration",
      "source": "nih_ai_news",
      "url": "https://www.nih.gov/news-events/news-releases/nih-scientists-develop-digital-twin-eye-cells-understand-treat-age-related-macular-degeneration",
      "published_date": "2026-03-20T16:54:12.320135+00:00",
      "category": "Government",
      "description": "Breakthrough modeling technology reveals how cells lose their organization in leading cause of vision loss.",
      "author": "",
      "content": "Breakthrough modeling technology reveals how cells lose their organization in leading cause of vision loss.",
      "consensus_multi_dimensional_score": {
        "relevance_score": 0.9,
        "quality_score": 0.9,
        "novelty_score": 0.8,
        "impact_score": 0.9,
        "overall_score": 0.8750000000000001,
        "confidence_mean": 0.8
      },
      "combined_deep_intelligence": {
        "analysis": {
          "fact_verification": {
            "verified_claims": [],
            "unverified_claims": [],
            "fact_check_confidence": 0.5
          },
          "bias_detection": {
            "bias_indicators": [],
            "bias_detection_score": 0.5
          },
          "credibility_assessment": {
            "credibility_factors": [],
            "credibility_score": 0.5
          },
          "impact_analysis": {
            "impact_areas": [],
            "impact_potential": 0.5
          },
          "synthesis": {
            "key_insights": [],
            "risk_factors": [],
            "enhancement_suggestions": []
          }
        },
        "score": 0.9,
        "confidence": 0.9,
        "recommendation": "ACCEPT",
        "agents_count": 1,
        "consensus_timestamp": "2026-03-20T16:58:32.439279+00:00"
      },
      "final_consensus": {
        "algorithm": "weighted_combination",
        "weighted_score": 0.74,
        "combined_confidence": 0.74,
        "decision": "ACCEPT",
        "weights": {
          "initial_consensus": 0.4,
          "deep_intelligence": 0.6
        },
        "timestamp": "2026-03-20T16:58:32.439284+00:00"
      },
      "article_type": "article"
    }
  ],
  "total_count": 15,
  "pipeline_version": "3.0_with_deep_intelligence"
}